CHANGELOG.txt
LICENSE.txt
MANIFEST.in
README.txt
setup.py
CSGOMemPy/__init__.py
CSGOMemPy.egg-info/PKG-INFO
CSGOMemPy.egg-info/SOURCES.txt
CSGOMemPy.egg-info/dependency_links.txt
CSGOMemPy.egg-info/requires.txt
CSGOMemPy.egg-info/top_level.txt